[
    {
        "id": 1,
        "question": "أفضل قضاء الوقت بمفردي أو مع عدد قليل من الأصدقاء المقربين بدلاً من المجموعات الكبيرة.",
        "letter": "I",
        "answers": [
            "أوافق بشدة",
            "أوافق",
            "محايد",
            "لا أوافق",
            "لا أوافق بشدة"
        ],
        "language_code": "ar"
    },
    {
        "id": 2,
        "question": "أستمتع بكوني محور الاهتمام في الفعاليات الاجتماعية.",
        "letter": "E",
        "answers": [
            "أوافق بشدة",
            "أوافق",
            "محايد",
            "لا أوافق",
            "لا أوافق بشدة"
        ],
        "language_code": "ar"
    },
    {
        "id": 3,
        "question": "أجد نفسي أحلم بمستقبل السيناريوهات والفرص.",
        "letter": "N",
        "answers": [
            "أوافق بشدة",
            "أوافق",
            "محايد",
            "لا أوافق",
            "لا أوافق بشدة"
        ],
        "language_code": "ar"
    },
    {
        "id": 4,
        "question": "أركز على التفاصيل والحقائق عند حل المشكلات.",
        "letter": "S",
        "answers": [
            "أوافق بشدة",
            "أوافق",
            "محايد",
            "لا أوافق",
            "لا أوافق بشدة"
        ],
        "language_code": "ar"
    },
    {
        "id": 5,
        "question": "أعتبر كيف ستؤثر قراراتي على مشاعر الآخرين ورفاهيتهم.",
        "letter": "F",
        "answers": [
            "أوافق بشدة",
            "أوافق",
            "محايد",
            "لا أوافق",
            "لا أوافق بشدة"
        ],
        "language_code": "ar"
    },
    {
        "id": 6,
        "question": "أتخذ قراراتي بناءً على المنطق والمعايير الموضوعية.",
        "letter": "T",
        "answers": [
            "أوافق بشدة",
            "أوافق",
            "محايد",
            "لا أوافق",
            "لا أوافق بشدة"
        ],
        "language_code": "ar"
    },
    {
        "id": 7,
        "question": "أشعر براحة أكبر عندما يمكنني التنبؤ بنتائج قراراتي.",
        "letter": "J",
        "answers": [
            "أوافق بشدة",
            "أوافق",
            "محايد",
            "لا أوافق",
            "لا أوافق بشدة"
        ],
        "language_code": "ar"
    },
    {
        "id": 8,
        "question": "أبقي خياراتي مفتوحة غالبًا وأتجنب اتخاذ قرارات سريعة.",
        "letter": "P",
        "answers": [
            "أوافق بشدة",
            "أوافق",
            "محايد",
            "لا أوافق",
            "لا أوافق بشدة"
        ],
        "language_code": "ar"
    },
    {
        "id": 9,
        "question": "أشعر بالتعب بعد فترات طويلة من التفاعل الاجتماعي.",
        "letter": "I",
        "answers": [
            "أوافق بشدة",
            "أوافق",
            "محايد",
            "لا أوافق",
            "لا أوافق بشدة"
        ],
        "language_code": "ar"
    },
    {
        "id": 10,
        "question": "أستمتع بكوني مرنًا والتكيف مع المعلومات أو الظروف الجديدة.",
        "letter": "P",
        "answers": [
            "أوافق بشدة",
            "أوافق",
            "محايد",
            "لا أوافق",
            "لا أوافق بشدة"
        ],
        "language_code": "ar"
    },
    {
        "id": 11,
        "question": "أفكر كثيرًا في الاحتمالات المستقبلية وما قد يحدث.",
        "letter": "N",
        "answers": [
            "أوافق بشدة",
            "أوافق",
            "محايد",
            "لا أوافق",
            "لا أوافق بشدة"
        ],
        "language_code": "ar"
    },
    {
        "id": 12,
        "question": "أثق في المعلومات التي يمكن ملاحظتها وقياسها.",
        "letter": "S",
        "answers": [
            "أوافق بشدة",
            "أوافق",
            "محايد",
            "لا أوافق",
            "لا أوافق بشدة"
        ],
        "language_code": "ar"
    },
    {
        "id": 13,
        "question": "أُقدّر الصدق والوضوح في النقاشات، حتى لو تسبب ذلك في توتر.",
        "letter": "T",
        "answers": [
            "أوافق بشدة",
            "أوافق",
            "محايد",
            "لا أوافق",
            "لا أوافق بشدة"
        ],
        "language_code": "ar"
    },
    {
        "id": 14,
        "question": "أُفضل الحفاظ على التناغم والعلاقات بدلاً من النتائج المنطقية البحتة.",
        "letter": "F",
        "answers": [
            "أوافق بشدة",
            "أوافق",
            "محايد",
            "لا أوافق",
            "لا أوافق بشدة"
        ],
        "language_code": "ar"
    },
    {
        "id": 15,
        "question": "أحب إتمام المهام قبل مواعيدها النهائية بفترة كبيرة.",
        "letter": "J",
        "answers": [
            "أوافق بشدة",
            "أوافق",
            "محايد",
            "لا أوافق",
            "لا أوافق بشدة"
        ],
        "language_code": "ar"
    },
    {
        "id": 16,
        "question": "أُفضل التجارب التعليمية العملية بدلاً من المناقشات النظرية.",
        "letter": "S",
        "answers": [
            "أوافق بشدة",
            "أوافق",
            "محايد",
            "لا أوافق",
            "لا أوافق بشدة"
        ],
        "language_code": "ar"
    },
    {
        "id": 17,
        "question": "أشعر بالنشاط بعد لقاء أشخاص جدد والمشاركة في محادثات.",
        "letter": "E",
        "answers": [
            "أوافق بشدة",
            "أوافق",
            "محايد",
            "لا أوافق",
            "لا أوافق بشدة"
        ],
        "language_code": "ar"
    },
    {
        "id": 18,
        "question": "أخذت وقتي للتفكير قبل التحدث في المواقف الاجتماعية.",
        "letter": "I",
        "answers": [
            "أوافق بشدة",
            "أوافق",
            "محايد",
            "لا أوافق",
            "لا أوافق بشدة"
        ],
        "language_code": "ar"
    },
    {
        "id": 19,
        "question": "أستمتع باتباع الإجراءات والأساليب المعتمدة عند إتمام المهام.",
        "letter": "S",
        "answers": [
            "أوافق بشدة",
            "أوافق",
            "محايد",
            "لا أوافق",
            "لا أوافق بشدة"
        ],
        "language_code": "ar"
    },
    {
        "id": 20,
        "question": "أجد من المثير اكتشاف الفرص الجديدة عندما تظهر.",
        "letter": "P",
        "answers": [
            "أوافق بشدة",
            "أوافق",
            "محايد",
            "لا أوافق",
            "لا أوافق بشدة"
        ],
        "language_code": "ar"
    },
    {
        "id": 21,
        "question": "أستمتع بالتعاون مع الآخرين وإيجاد أرضية مشتركة في النقاشات.",
        "letter": "F",
        "answers": [
            "أوافق بشدة",
            "أوافق",
            "محايد",
            "لا أوافق",
            "لا أوافق بشدة"
        ],
        "language_code": "ar"
    },
    {
        "id": 22,
        "question": "أُفضل أن يكون لدي خطة منظمة قبل بدء أي مشروع.",
        "letter": "J",
        "answers": [
            "أوافق بشدة",
            "أوافق",
            "محايد",
            "لا أوافق",
            "لا أوافق بشدة"
        ],
        "language_code": "ar"
    },
    {
        "id": 23,
        "question": "أُعير انتباهي للتجارب الحسية والتفاصيل في بيئتي.",
        "letter": "S",
        "answers": [
            "أوافق بشدة",
            "أوافق",
            "محايد",
            "لا أوافق",
            "لا أوافق بشدة"
        ],
        "language_code": "ar"
    },
    {
        "id": 24,
        "question": "أعبّر غالبًا عن مشاعري بصراحة وأشجع الآخرين على فعل الشيء نفسه.",
        "letter": "F",
        "answers": [
            "أوافق بشدة",
            "أوافق",
            "محايد",
            "لا أوافق",
            "لا أوافق بشدة"
        ],
        "language_code": "ar"
    },
    {
        "id": 25,
        "question": "أحب الانخراط في مناقشات مع مجموعة كبيرة من الأشخاص.",
        "letter": "E",
        "answers": [
            "أوافق بشدة",
            "أوافق",
            "محايد",
            "لا أوافق",
            "لا أوافق بشدة"
        ],
        "language_code": "ar"
    },
    {
        "id": 26,
        "question": "أُفضل النظر إلى الصورة الكبيرة بدلاً من التفاصيل.",
        "letter": "N",
        "answers": [
            "أوافق بشدة",
            "أوافق",
            "محايد",
            "لا أوافق",
            "لا أوافق بشدة"
        ],
        "language_code": "ar"
    },
    {
        "id": 27,
        "question": "أحلل غالبًا المواقف بشكل نقدي بدلاً من عاطفي.",
        "letter": "T",
        "answers": [
            "أوافق بشدة",
            "أوافق",
            "محايد",
            "لا أوافق",
            "لا أوافق بشدة"
        ],
        "language_code": "ar"
    },
    {
        "id": 28,
        "question": "أشعر بالإنجاز عندما يمكنني مساعدة الآخرين أو إحداث تأثير إيجابي في حياتهم.",
        "letter": "F",
        "answers": [
            "أوافق بشدة",
            "أوافق",
            "محايد",
            "لا أوافق",
            "لا أوافق بشدة"
        ],
        "language_code": "ar"
    },
    {
        "id": 29,
        "question": "أستمتع بأن أكون عفويًا وتغيير الخطط حسب الحاجة.",
        "letter": "P",
        "answers": [
            "أوافق بشدة",
            "أوافق",
            "محايد",
            "لا أوافق",
            "لا أوافق بشدة"
        ],
        "language_code": "ar"
    },
    {
        "id": 30,
        "question": "أشعر بالنشاط بعد قضاء الوقت في بيئة حيوية.",
        "letter": "E",
        "answers": [
            "أوافق بشدة",
            "أوافق",
            "محايد",
            "لا أوافق",
            "لا أوافق بشدة"
        ],
        "language_code": "ar"
    },
    {
        "id": 31,
        "question": "أحب استكشاف الأفكار والمفاهيم المجردة.",
        "letter": "N",
        "answers": [
            "أوافق بشدة",
            "أوافق",
            "محايد",
            "لا أوافق",
            "لا أوافق بشدة"
        ],
        "language_code": "ar"
    },
    {
        "id": 32,
        "question": "أُفضل حل النزاعات من خلال التركيز على الحقائق بدلاً من المشاعر.",
        "letter": "T",
        "answers": [
            "أوافق بشدة",
            "أوافق",
            "محايد",
            "لا أوافق",
            "لا أوافق بشدة"
        ],
        "language_code": "ar"
    },
    {
        "id": 33,
        "question": "أحب أن يكون لدي قواعد وإرشادات واضحة في حياتي اليومية.",
        "letter": "J",
        "answers": [
            "أوافق بشدة",
            "أوافق",
            "محايد",
            "لا أوافق",
            "لا أوافق بشدة"
        ],
        "language_code": "ar"
    },
    {
        "id": 34,
        "question": "أحب بدء محادثات مع الغرباء.",
        "letter": "E",
        "answers": [
            "أوافق بشدة",
            "أوافق",
            "محايد",
            "لا أوافق",
            "لا أوافق بشدة"
        ],
        "language_code": "ar"
    },
    {
        "id": 35,
        "question": "أجد صعوبة في العمل في بيئة غير منظمة أو فوضوية.",
        "letter": "J",
        "answers": [
            "أوافق بشدة",
            "أوافق",
            "محايد",
            "لا أوافق",
            "لا أوافق بشدة"
        ],
        "language_code": "ar"
    },
    {
        "id": 36,
        "question": "أشعر غالبًا بالارتباك بسبب كثرة الخيارات.",
        "letter": "P",
        "answers": [
            "أوافق بشدة",
            "أوافق",
            "محايد",
            "لا أوافق",
            "لا أوافق بشدة"
        ],
        "language_code": "ar"
    },
    {
        "id": 37,
        "question": "أثق في حدسي عند اتخاذ القرارات.",
        "letter": "N",
        "answers": [
            "أوافق بشدة",
            "أوافق",
            "محايد",
            "لا أوافق",
            "لا أوافق بشدة"
        ],
        "language_code": "ar"
    },
    {
        "id": 38,
        "question": "أبحث غالبًا عن أنشطة جماعية أو تجمعات اجتماعية في وقت فراغي.",
        "letter": "E",
        "answers": [
            "أوافق بشدة",
            "أوافق",
            "محايد",
            "لا أوافق",
            "لا أوافق بشدة"
        ],
        "language_code": "ar"
    },
    {
        "id": 39,
        "question": "أستمتع بمناقشة المفاهيم النظرية والاحتمالات المستقبلية.",
        "letter": "N",
        "answers": [
            "أوافق بشدة",
            "أوافق",
            "محايد",
            "لا أوافق",
            "لا أوافق بشدة"
        ],
        "language_code": "ar"
    },
    {
        "id": 40,
        "question": "أُفضل التفكير في الأمور قبل مشاركة أفكاري مع الآخرين.",
        "letter": "I",
        "answers": [
            "أوافق بشدة",
            "أوافق",
            "محايد",
            "لا أوافق",
            "لا أوافق بشدة"
        ],
        "language_code": "ar"
    }
]